{
  "chainSlug": "ippudo",
  "chainName": "一風堂",
  "restaurantType": "dining",
  "category": "その他",
  "aliases": [
    "一風堂",
    "ippudo",
    "IPPUDO"
  ],
  "attribution": "公式 PDF (一風堂) — kcal は公開値、 PFC は AI 推定 (Drafting 136 ramen-ratio)",
  "attributionUrl": "https://storage.googleapis.com/studio-design-asset-files/projects/JpOL0L4xOQ/s-1x1_da3e772d-ae83-43cb-84d8-c867ddfe2fc7.pdf",
  "sourceCapturedAt": "2026-05-18",
  "menuItems": [
    {
      "name": "白丸元味",
      "servingSizeG": 100,
      "servingUnit": "杯",
      "caloriesPerServing": 659,
      "proteinG": 26.4,
      "fatG": 22,
      "carbG": 89,
      "source": "ai_estimate",
      "sourceUrl": "https://storage.googleapis.com/studio-design-asset-files/projects/JpOL0L4xOQ/s-1x1_da3e772d-ae83-43cb-84d8-c867ddfe2fc7.pdf",
      "sourceCapturedAt": "2026-05-18"
    },
    {
      "name": "赤丸新味",
      "servingSizeG": 100,
      "servingUnit": "杯",
      "caloriesPerServing": 914,
      "proteinG": 36.6,
      "fatG": 30.5,
      "carbG": 123.4,
      "source": "ai_estimate",
      "sourceUrl": "https://storage.googleapis.com/studio-design-asset-files/projects/JpOL0L4xOQ/s-1x1_da3e772d-ae83-43cb-84d8-c867ddfe2fc7.pdf",
      "sourceCapturedAt": "2026-05-18"
    },
    {
      "name": "からか麺",
      "servingSizeG": 100,
      "servingUnit": "杯",
      "caloriesPerServing": 749,
      "proteinG": 30,
      "fatG": 25,
      "carbG": 101.1,
      "source": "ai_estimate",
      "sourceUrl": "https://storage.googleapis.com/studio-design-asset-files/projects/JpOL0L4xOQ/s-1x1_da3e772d-ae83-43cb-84d8-c867ddfe2fc7.pdf",
      "sourceCapturedAt": "2026-05-18"
    },
    {
      "name": "ラーメン・ごはん",
      "servingSizeG": 100,
      "servingUnit": "杯",
      "caloriesPerServing": 633,
      "proteinG": 25.3,
      "fatG": 21.1,
      "carbG": 85.5,
      "source": "ai_estimate",
      "sourceUrl": "https://storage.googleapis.com/studio-design-asset-files/projects/JpOL0L4xOQ/s-1x1_da3e772d-ae83-43cb-84d8-c867ddfe2fc7.pdf",
      "sourceCapturedAt": "2026-05-18"
    },
    {
      "name": "ラーメン",
      "servingSizeG": 100,
      "servingUnit": "杯",
      "caloriesPerServing": 452,
      "proteinG": 18.1,
      "fatG": 15.1,
      "carbG": 61,
      "source": "ai_estimate",
      "sourceUrl": "https://storage.googleapis.com/studio-design-asset-files/projects/JpOL0L4xOQ/s-1x1_da3e772d-ae83-43cb-84d8-c867ddfe2fc7.pdf",
      "sourceCapturedAt": "2026-05-18"
    },
    {
      "name": "替玉（ラーメンのたれ含む）",
      "servingSizeG": 100,
      "servingUnit": "杯",
      "caloriesPerServing": 281,
      "proteinG": 11.2,
      "fatG": 9.4,
      "carbG": 37.9,
      "source": "ai_estimate",
      "sourceUrl": "https://storage.googleapis.com/studio-design-asset-files/projects/JpOL0L4xOQ/s-1x1_da3e772d-ae83-43cb-84d8-c867ddfe2fc7.pdf",
      "sourceCapturedAt": "2026-05-18"
    },
    {
      "name": "トッピング温泉玉子",
      "servingSizeG": 100,
      "servingUnit": "杯",
      "caloriesPerServing": 75,
      "proteinG": 3,
      "fatG": 2.5,
      "carbG": 10.1,
      "source": "ai_estimate",
      "sourceUrl": "https://storage.googleapis.com/studio-design-asset-files/projects/JpOL0L4xOQ/s-1x1_da3e772d-ae83-43cb-84d8-c867ddfe2fc7.pdf",
      "sourceCapturedAt": "2026-05-18"
    },
    {
      "name": "トッピングきくらげ",
      "servingSizeG": 100,
      "servingUnit": "杯",
      "caloriesPerServing": 40,
      "proteinG": 1.6,
      "fatG": 1.3,
      "carbG": 5.4,
      "source": "ai_estimate",
      "sourceUrl": "https://storage.googleapis.com/studio-design-asset-files/projects/JpOL0L4xOQ/s-1x1_da3e772d-ae83-43cb-84d8-c867ddfe2fc7.pdf",
      "sourceCapturedAt": "2026-05-18"
    },
    {
      "name": "トッピングのり",
      "servingSizeG": 100,
      "servingUnit": "杯",
      "caloriesPerServing": 5,
      "proteinG": 0.2,
      "fatG": 0.2,
      "carbG": 0.7,
      "source": "ai_estimate",
      "sourceUrl": "https://storage.googleapis.com/studio-design-asset-files/projects/JpOL0L4xOQ/s-1x1_da3e772d-ae83-43cb-84d8-c867ddfe2fc7.pdf",
      "sourceCapturedAt": "2026-05-18"
    },
    {
      "name": "トッピングねぎ",
      "servingSizeG": 100,
      "servingUnit": "杯",
      "caloriesPerServing": 10,
      "proteinG": 0.4,
      "fatG": 0.3,
      "carbG": 1.4,
      "source": "ai_estimate",
      "sourceUrl": "https://storage.googleapis.com/studio-design-asset-files/projects/JpOL0L4xOQ/s-1x1_da3e772d-ae83-43cb-84d8-c867ddfe2fc7.pdf",
      "sourceCapturedAt": "2026-05-18"
    },
    {
      "name": "トッピング低温調理ロースチャーシュー（2枚）",
      "servingSizeG": 100,
      "servingUnit": "杯",
      "caloriesPerServing": 59,
      "proteinG": 2.4,
      "fatG": 2,
      "carbG": 8,
      "source": "ai_estimate",
      "sourceUrl": "https://storage.googleapis.com/studio-design-asset-files/projects/JpOL0L4xOQ/s-1x1_da3e772d-ae83-43cb-84d8-c867ddfe2fc7.pdf",
      "sourceCapturedAt": "2026-05-18"
    },
    {
      "name": "トッピング厚切りバラチャーシュー（１枚）",
      "servingSizeG": 100,
      "servingUnit": "杯",
      "caloriesPerServing": 124,
      "proteinG": 5,
      "fatG": 4.1,
      "carbG": 16.7,
      "source": "ai_estimate",
      "sourceUrl": "https://storage.googleapis.com/studio-design-asset-files/projects/JpOL0L4xOQ/s-1x1_da3e772d-ae83-43cb-84d8-c867ddfe2fc7.pdf",
      "sourceCapturedAt": "2026-05-18"
    },
    {
      "name": "トッピングタンメン野菜",
      "servingSizeG": 100,
      "servingUnit": "杯",
      "caloriesPerServing": 120,
      "proteinG": 4.8,
      "fatG": 4,
      "carbG": 16.2,
      "source": "ai_estimate",
      "sourceUrl": "https://storage.googleapis.com/studio-design-asset-files/projects/JpOL0L4xOQ/s-1x1_da3e772d-ae83-43cb-84d8-c867ddfe2fc7.pdf",
      "sourceCapturedAt": "2026-05-18"
    },
    {
      "name": "トッピング明太子",
      "servingSizeG": 100,
      "servingUnit": "杯",
      "caloriesPerServing": 25,
      "proteinG": 1,
      "fatG": 0.8,
      "carbG": 3.4,
      "source": "ai_estimate",
      "sourceUrl": "https://storage.googleapis.com/studio-design-asset-files/projects/JpOL0L4xOQ/s-1x1_da3e772d-ae83-43cb-84d8-c867ddfe2fc7.pdf",
      "sourceCapturedAt": "2026-05-18"
    },
    {
      "name": "辛味ソース",
      "servingSizeG": 100,
      "servingUnit": "杯",
      "caloriesPerServing": 45,
      "proteinG": 1.8,
      "fatG": 1.5,
      "carbG": 6.1,
      "source": "ai_estimate",
      "sourceUrl": "https://storage.googleapis.com/studio-design-asset-files/projects/JpOL0L4xOQ/s-1x1_da3e772d-ae83-43cb-84d8-c867ddfe2fc7.pdf",
      "sourceCapturedAt": "2026-05-18"
    },
    {
      "name": "博多ひとくち餃子(餃子のたれを含む)",
      "servingSizeG": 100,
      "servingUnit": "杯",
      "caloriesPerServing": 320,
      "proteinG": 12.8,
      "fatG": 10.7,
      "carbG": 43.2,
      "source": "ai_estimate",
      "sourceUrl": "https://storage.googleapis.com/studio-design-asset-files/projects/JpOL0L4xOQ/s-1x1_da3e772d-ae83-43cb-84d8-c867ddfe2fc7.pdf",
      "sourceCapturedAt": "2026-05-18"
    },
    {
      "name": "博多チャーハン",
      "servingSizeG": 100,
      "servingUnit": "杯",
      "caloriesPerServing": 850,
      "proteinG": 34,
      "fatG": 28.3,
      "carbG": 114.8,
      "source": "ai_estimate",
      "sourceUrl": "https://storage.googleapis.com/studio-design-asset-files/projects/JpOL0L4xOQ/s-1x1_da3e772d-ae83-43cb-84d8-c867ddfe2fc7.pdf",
      "sourceCapturedAt": "2026-05-18"
    },
    {
      "name": "温玉ごはん",
      "servingSizeG": 100,
      "servingUnit": "杯",
      "caloriesPerServing": 335,
      "proteinG": 13.4,
      "fatG": 11.2,
      "carbG": 45.2,
      "source": "ai_estimate",
      "sourceUrl": "https://storage.googleapis.com/studio-design-asset-files/projects/JpOL0L4xOQ/s-1x1_da3e772d-ae83-43cb-84d8-c867ddfe2fc7.pdf",
      "sourceCapturedAt": "2026-05-18"
    },
    {
      "name": "明太子ごはん",
      "servingSizeG": 100,
      "servingUnit": "杯",
      "caloriesPerServing": 375,
      "proteinG": 15,
      "fatG": 12.5,
      "carbG": 50.6,
      "source": "ai_estimate",
      "sourceUrl": "https://storage.googleapis.com/studio-design-asset-files/projects/JpOL0L4xOQ/s-1x1_da3e772d-ae83-43cb-84d8-c867ddfe2fc7.pdf",
      "sourceCapturedAt": "2026-05-18"
    },
    {
      "name": "温玉のせ明太子ごはん",
      "servingSizeG": 100,
      "servingUnit": "杯",
      "caloriesPerServing": 450,
      "proteinG": 18,
      "fatG": 15,
      "carbG": 60.8,
      "source": "ai_estimate",
      "sourceUrl": "https://storage.googleapis.com/studio-design-asset-files/projects/JpOL0L4xOQ/s-1x1_da3e772d-ae83-43cb-84d8-c867ddfe2fc7.pdf",
      "sourceCapturedAt": "2026-05-18"
    },
    {
      "name": "チャーシューまぶしごはん",
      "servingSizeG": 100,
      "servingUnit": "杯",
      "caloriesPerServing": 454,
      "proteinG": 18.2,
      "fatG": 15.1,
      "carbG": 61.3,
      "source": "ai_estimate",
      "sourceUrl": "https://storage.googleapis.com/studio-design-asset-files/projects/JpOL0L4xOQ/s-1x1_da3e772d-ae83-43cb-84d8-c867ddfe2fc7.pdf",
      "sourceCapturedAt": "2026-05-18"
    },
    {
      "name": "辛もやし（1食あたり約50g）",
      "servingSizeG": 100,
      "servingUnit": "杯",
      "caloriesPerServing": 25,
      "proteinG": 1,
      "fatG": 0.8,
      "carbG": 3.4,
      "source": "ai_estimate",
      "sourceUrl": "https://storage.googleapis.com/studio-design-asset-files/projects/JpOL0L4xOQ/s-1x1_da3e772d-ae83-43cb-84d8-c867ddfe2fc7.pdf",
      "sourceCapturedAt": "2026-05-18"
    },
    {
      "name": "紅生姜（1食あたり約15g）",
      "servingSizeG": 100,
      "servingUnit": "杯",
      "caloriesPerServing": 3,
      "proteinG": 0.1,
      "fatG": 0.1,
      "carbG": 0.4,
      "source": "ai_estimate",
      "sourceUrl": "https://storage.googleapis.com/studio-design-asset-files/projects/JpOL0L4xOQ/s-1x1_da3e772d-ae83-43cb-84d8-c867ddfe2fc7.pdf",
      "sourceCapturedAt": "2026-05-18"
    },
    {
      "name": "辛子高菜（1食あたり約20g）",
      "servingSizeG": 100,
      "servingUnit": "杯",
      "caloriesPerServing": 15,
      "proteinG": 0.6,
      "fatG": 0.5,
      "carbG": 2,
      "source": "ai_estimate",
      "sourceUrl": "https://storage.googleapis.com/studio-design-asset-files/projects/JpOL0L4xOQ/s-1x1_da3e772d-ae83-43cb-84d8-c867ddfe2fc7.pdf",
      "sourceCapturedAt": "2026-05-18"
    },
    {
      "name": "担々麵（りんくうプレミアムアウトレット店 限定）",
      "servingSizeG": 100,
      "servingUnit": "杯",
      "caloriesPerServing": 886,
      "proteinG": 35.4,
      "fatG": 29.5,
      "carbG": 119.6,
      "source": "ai_estimate",
      "sourceUrl": "https://storage.googleapis.com/studio-design-asset-files/projects/JpOL0L4xOQ/s-1x1_da3e772d-ae83-43cb-84d8-c867ddfe2fc7.pdf",
      "sourceCapturedAt": "2026-05-18"
    },
    {
      "name": "とんこつ醤油(販売店舗リストはこちら)",
      "servingSizeG": 100,
      "servingUnit": "杯",
      "caloriesPerServing": 819,
      "proteinG": 32.8,
      "fatG": 27.3,
      "carbG": 110.6,
      "source": "ai_estimate",
      "sourceUrl": "https://storage.googleapis.com/studio-design-asset-files/projects/JpOL0L4xOQ/s-1x1_da3e772d-ae83-43cb-84d8-c867ddfe2fc7.pdf",
      "sourceCapturedAt": "2026-05-18"
    },
    {
      "name": "プラント赤丸(販売店舗はこちら)",
      "servingSizeG": 100,
      "servingUnit": "杯",
      "caloriesPerServing": 778,
      "proteinG": 31.1,
      "fatG": 25.9,
      "carbG": 105,
      "source": "ai_estimate",
      "sourceUrl": "https://storage.googleapis.com/studio-design-asset-files/projects/JpOL0L4xOQ/s-1x1_da3e772d-ae83-43cb-84d8-c867ddfe2fc7.pdf",
      "sourceCapturedAt": "2026-05-18"
    },
    {
      "name": "プラント赤丸(梅田店、長堀店（万博特別企画）)",
      "servingSizeG": 100,
      "servingUnit": "杯",
      "caloriesPerServing": 778,
      "proteinG": 31.1,
      "fatG": 25.9,
      "carbG": 105,
      "source": "ai_estimate",
      "sourceUrl": "https://storage.googleapis.com/studio-design-asset-files/projects/JpOL0L4xOQ/s-1x1_da3e772d-ae83-43cb-84d8-c867ddfe2fc7.pdf",
      "sourceCapturedAt": "2026-05-18"
    },
    {
      "name": "プラント白丸(原宿竹下通り店)",
      "servingSizeG": 100,
      "servingUnit": "杯",
      "caloriesPerServing": 611,
      "proteinG": 24.4,
      "fatG": 20.4,
      "carbG": 82.5,
      "source": "ai_estimate",
      "sourceUrl": "https://storage.googleapis.com/studio-design-asset-files/projects/JpOL0L4xOQ/s-1x1_da3e772d-ae83-43cb-84d8-c867ddfe2fc7.pdf",
      "sourceCapturedAt": "2026-05-18"
    },
    {
      "name": "川越とんこつ醬油（川越インター店 限定）",
      "servingSizeG": 100,
      "servingUnit": "杯",
      "caloriesPerServing": 963,
      "proteinG": 38.5,
      "fatG": 32.1,
      "carbG": 130,
      "source": "ai_estimate",
      "sourceUrl": "https://storage.googleapis.com/studio-design-asset-files/projects/JpOL0L4xOQ/s-1x1_da3e772d-ae83-43cb-84d8-c867ddfe2fc7.pdf",
      "sourceCapturedAt": "2026-05-18"
    },
    {
      "name": "博多中華そば(販売店舗リストはこちら)",
      "servingSizeG": 100,
      "servingUnit": "杯",
      "caloriesPerServing": 630,
      "proteinG": 25.2,
      "fatG": 21,
      "carbG": 85.1,
      "source": "ai_estimate",
      "sourceUrl": "https://storage.googleapis.com/studio-design-asset-files/projects/JpOL0L4xOQ/s-1x1_da3e772d-ae83-43cb-84d8-c867ddfe2fc7.pdf",
      "sourceCapturedAt": "2026-05-18"
    },
    {
      "name": "博多塩中華そば（宗像店 限定）",
      "servingSizeG": 100,
      "servingUnit": "杯",
      "caloriesPerServing": 676,
      "proteinG": 27,
      "fatG": 22.5,
      "carbG": 91.3,
      "source": "ai_estimate",
      "sourceUrl": "https://storage.googleapis.com/studio-design-asset-files/projects/JpOL0L4xOQ/s-1x1_da3e772d-ae83-43cb-84d8-c867ddfe2fc7.pdf",
      "sourceCapturedAt": "2026-05-18"
    },
    {
      "name": "醤油豚骨(堺インター店、堀江店 限定)",
      "servingSizeG": 100,
      "servingUnit": "杯",
      "caloriesPerServing": 960,
      "proteinG": 38.4,
      "fatG": 32,
      "carbG": 129.6,
      "source": "ai_estimate",
      "sourceUrl": "https://storage.googleapis.com/studio-design-asset-files/projects/JpOL0L4xOQ/s-1x1_da3e772d-ae83-43cb-84d8-c867ddfe2fc7.pdf",
      "sourceCapturedAt": "2026-05-18"
    },
    {
      "name": "醤油豚骨（ゆめタウン久留米店 限定）",
      "servingSizeG": 100,
      "servingUnit": "杯",
      "caloriesPerServing": 686,
      "proteinG": 27.4,
      "fatG": 22.9,
      "carbG": 92.6,
      "source": "ai_estimate",
      "sourceUrl": "https://storage.googleapis.com/studio-design-asset-files/projects/JpOL0L4xOQ/s-1x1_da3e772d-ae83-43cb-84d8-c867ddfe2fc7.pdf",
      "sourceCapturedAt": "2026-05-18"
    },
    {
      "name": "江戸式醤油麺（浅草橋本舗、亀有店限定）",
      "servingSizeG": 100,
      "servingUnit": "杯",
      "caloriesPerServing": 764,
      "proteinG": 30.6,
      "fatG": 25.5,
      "carbG": 103.1,
      "source": "ai_estimate",
      "sourceUrl": "https://storage.googleapis.com/studio-design-asset-files/projects/JpOL0L4xOQ/s-1x1_da3e772d-ae83-43cb-84d8-c867ddfe2fc7.pdf",
      "sourceCapturedAt": "2026-05-18"
    },
    {
      "name": "博多源流醤油（六本木店 限定）",
      "servingSizeG": 100,
      "servingUnit": "杯",
      "caloriesPerServing": 812,
      "proteinG": 32.5,
      "fatG": 27.1,
      "carbG": 109.6,
      "source": "ai_estimate",
      "sourceUrl": "https://storage.googleapis.com/studio-design-asset-files/projects/JpOL0L4xOQ/s-1x1_da3e772d-ae83-43cb-84d8-c867ddfe2fc7.pdf",
      "sourceCapturedAt": "2026-05-18"
    },
    {
      "name": "佐野タンメン(白ご飯付)（佐野高萩店 限定）",
      "servingSizeG": 100,
      "servingUnit": "杯",
      "caloriesPerServing": 955,
      "proteinG": 38.2,
      "fatG": 31.8,
      "carbG": 128.9,
      "source": "ai_estimate",
      "sourceUrl": "https://storage.googleapis.com/studio-design-asset-files/projects/JpOL0L4xOQ/s-1x1_da3e772d-ae83-43cb-84d8-c867ddfe2fc7.pdf",
      "sourceCapturedAt": "2026-05-18"
    },
    {
      "name": "健軍タンメン(白ご飯付)（健軍東店 限定）",
      "servingSizeG": 100,
      "servingUnit": "杯",
      "caloriesPerServing": 983,
      "proteinG": 39.3,
      "fatG": 32.8,
      "carbG": 132.7,
      "source": "ai_estimate",
      "sourceUrl": "https://storage.googleapis.com/studio-design-asset-files/projects/JpOL0L4xOQ/s-1x1_da3e772d-ae83-43cb-84d8-c867ddfe2fc7.pdf",
      "sourceCapturedAt": "2026-05-18"
    },
    {
      "name": "健軍タンメン唐揚げのせ(白ご飯付)（健軍東店 限定）",
      "servingSizeG": 100,
      "servingUnit": "杯",
      "caloriesPerServing": 1119,
      "proteinG": 44.8,
      "fatG": 37.3,
      "carbG": 151.1,
      "source": "ai_estimate",
      "sourceUrl": "https://storage.googleapis.com/studio-design-asset-files/projects/JpOL0L4xOQ/s-1x1_da3e772d-ae83-43cb-84d8-c867ddfe2fc7.pdf",
      "sourceCapturedAt": "2026-05-18"
    },
    {
      "name": "店、六本木店、太宰府ｲﾝﾀｰ店 限定)",
      "servingSizeG": 100,
      "servingUnit": "杯",
      "caloriesPerServing": 539,
      "proteinG": 21.6,
      "fatG": 18,
      "carbG": 72.8,
      "source": "ai_estimate",
      "sourceUrl": "https://storage.googleapis.com/studio-design-asset-files/projects/JpOL0L4xOQ/s-1x1_da3e772d-ae83-43cb-84d8-c867ddfe2fc7.pdf",
      "sourceCapturedAt": "2026-05-18"
    },
    {
      "name": "唐揚げ（堺インター店）",
      "servingSizeG": 100,
      "servingUnit": "杯",
      "caloriesPerServing": 536,
      "proteinG": 21.4,
      "fatG": 17.9,
      "carbG": 72.4,
      "source": "ai_estimate",
      "sourceUrl": "https://storage.googleapis.com/studio-design-asset-files/projects/JpOL0L4xOQ/s-1x1_da3e772d-ae83-43cb-84d8-c867ddfe2fc7.pdf",
      "sourceCapturedAt": "2026-05-18"
    },
    {
      "name": "唐揚げ",
      "servingSizeG": 100,
      "servingUnit": "杯",
      "caloriesPerServing": 329,
      "proteinG": 13.2,
      "fatG": 11,
      "carbG": 44.4,
      "source": "ai_estimate",
      "sourceUrl": "https://storage.googleapis.com/studio-design-asset-files/projects/JpOL0L4xOQ/s-1x1_da3e772d-ae83-43cb-84d8-c867ddfe2fc7.pdf",
      "sourceCapturedAt": "2026-05-18"
    },
    {
      "name": "キャベツサラダ",
      "servingSizeG": 100,
      "servingUnit": "杯",
      "caloriesPerServing": 18,
      "proteinG": 0.7,
      "fatG": 0.6,
      "carbG": 2.4,
      "source": "ai_estimate",
      "sourceUrl": "https://storage.googleapis.com/studio-design-asset-files/projects/JpOL0L4xOQ/s-1x1_da3e772d-ae83-43cb-84d8-c867ddfe2fc7.pdf",
      "sourceCapturedAt": "2026-05-18"
    },
    {
      "name": "ポテトフライ(LECT広島店、ゆめタウン高松店、ゆめタウン徳島店限定)",
      "servingSizeG": 100,
      "servingUnit": "杯",
      "caloriesPerServing": 575,
      "proteinG": 23,
      "fatG": 19.2,
      "carbG": 77.6,
      "source": "ai_estimate",
      "sourceUrl": "https://storage.googleapis.com/studio-design-asset-files/projects/JpOL0L4xOQ/s-1x1_da3e772d-ae83-43cb-84d8-c867ddfe2fc7.pdf",
      "sourceCapturedAt": "2026-05-18"
    },
    {
      "name": "水餃子(四条烏丸店、銀座インズ店、ルミネ大宮店 限定)",
      "servingSizeG": 100,
      "servingUnit": "杯",
      "caloriesPerServing": 160,
      "proteinG": 6.4,
      "fatG": 5.3,
      "carbG": 21.6,
      "source": "ai_estimate",
      "sourceUrl": "https://storage.googleapis.com/studio-design-asset-files/projects/JpOL0L4xOQ/s-1x1_da3e772d-ae83-43cb-84d8-c867ddfe2fc7.pdf",
      "sourceCapturedAt": "2026-05-18"
    },
    {
      "name": "本店白丸",
      "servingSizeG": 100,
      "servingUnit": "杯",
      "caloriesPerServing": 713,
      "proteinG": 28.5,
      "fatG": 23.8,
      "carbG": 96.3,
      "source": "ai_estimate",
      "sourceUrl": "https://storage.googleapis.com/studio-design-asset-files/projects/JpOL0L4xOQ/s-1x1_da3e772d-ae83-43cb-84d8-c867ddfe2fc7.pdf",
      "sourceCapturedAt": "2026-05-18"
    },
    {
      "name": "本店赤丸",
      "servingSizeG": 100,
      "servingUnit": "杯",
      "caloriesPerServing": 848,
      "proteinG": 33.9,
      "fatG": 28.3,
      "carbG": 114.5,
      "source": "ai_estimate",
      "sourceUrl": "https://storage.googleapis.com/studio-design-asset-files/projects/JpOL0L4xOQ/s-1x1_da3e772d-ae83-43cb-84d8-c867ddfe2fc7.pdf",
      "sourceCapturedAt": "2026-05-18"
    },
    {
      "name": "博多しょうゆらぁめん",
      "servingSizeG": 100,
      "servingUnit": "杯",
      "caloriesPerServing": 620,
      "proteinG": 24.8,
      "fatG": 20.7,
      "carbG": 83.7,
      "source": "ai_estimate",
      "sourceUrl": "https://storage.googleapis.com/studio-design-asset-files/projects/JpOL0L4xOQ/s-1x1_da3e772d-ae83-43cb-84d8-c867ddfe2fc7.pdf",
      "sourceCapturedAt": "2026-05-18"
    },
    {
      "name": "チャーシューごはん",
      "servingSizeG": 100,
      "servingUnit": "杯",
      "caloriesPerServing": 580,
      "proteinG": 23.2,
      "fatG": 19.3,
      "carbG": 78.3,
      "source": "ai_estimate",
      "sourceUrl": "https://storage.googleapis.com/studio-design-asset-files/projects/JpOL0L4xOQ/s-1x1_da3e772d-ae83-43cb-84d8-c867ddfe2fc7.pdf",
      "sourceCapturedAt": "2026-05-18"
    },
    {
      "name": "チャーシューごはん(ランチセット)",
      "servingSizeG": 100,
      "servingUnit": "杯",
      "caloriesPerServing": 542,
      "proteinG": 21.7,
      "fatG": 18.1,
      "carbG": 73.2,
      "source": "ai_estimate",
      "sourceUrl": "https://storage.googleapis.com/studio-design-asset-files/projects/JpOL0L4xOQ/s-1x1_da3e772d-ae83-43cb-84d8-c867ddfe2fc7.pdf",
      "sourceCapturedAt": "2026-05-18"
    },
    {
      "name": "チャーシュー炙り明太マヨ丼",
      "servingSizeG": 100,
      "servingUnit": "杯",
      "caloriesPerServing": 328,
      "proteinG": 13.1,
      "fatG": 10.9,
      "carbG": 44.3,
      "source": "ai_estimate",
      "sourceUrl": "https://storage.googleapis.com/studio-design-asset-files/projects/JpOL0L4xOQ/s-1x1_da3e772d-ae83-43cb-84d8-c867ddfe2fc7.pdf",
      "sourceCapturedAt": "2026-05-18"
    },
    {
      "name": "博多まつりめし",
      "servingSizeG": 100,
      "servingUnit": "杯",
      "caloriesPerServing": 312,
      "proteinG": 12.5,
      "fatG": 10.4,
      "carbG": 42.1,
      "source": "ai_estimate",
      "sourceUrl": "https://storage.googleapis.com/studio-design-asset-files/projects/JpOL0L4xOQ/s-1x1_da3e772d-ae83-43cb-84d8-c867ddfe2fc7.pdf",
      "sourceCapturedAt": "2026-05-18"
    },
    {
      "name": "スカイバンズ",
      "servingSizeG": 100,
      "servingUnit": "杯",
      "caloriesPerServing": 213,
      "proteinG": 8.5,
      "fatG": 7.1,
      "carbG": 28.8,
      "source": "ai_estimate",
      "sourceUrl": "https://storage.googleapis.com/studio-design-asset-files/projects/JpOL0L4xOQ/s-1x1_da3e772d-ae83-43cb-84d8-c867ddfe2fc7.pdf",
      "sourceCapturedAt": "2026-05-18"
    },
    {
      "name": "糸島黒とんこつ",
      "servingSizeG": 100,
      "servingUnit": "杯",
      "caloriesPerServing": 906,
      "proteinG": 36.2,
      "fatG": 30.2,
      "carbG": 122.3,
      "source": "ai_estimate",
      "sourceUrl": "https://storage.googleapis.com/studio-design-asset-files/projects/JpOL0L4xOQ/s-1x1_da3e772d-ae83-43cb-84d8-c867ddfe2fc7.pdf",
      "sourceCapturedAt": "2026-05-18"
    },
    {
      "name": "特製絹ごしベジとんこつ ミラとん",
      "servingSizeG": 100,
      "servingUnit": "杯",
      "caloriesPerServing": 683,
      "proteinG": 27.3,
      "fatG": 22.8,
      "carbG": 92.2,
      "source": "ai_estimate",
      "sourceUrl": "https://storage.googleapis.com/studio-design-asset-files/projects/JpOL0L4xOQ/s-1x1_da3e772d-ae83-43cb-84d8-c867ddfe2fc7.pdf",
      "sourceCapturedAt": "2026-05-18"
    },
    {
      "name": "大地香る醤油ラーメン",
      "servingSizeG": 100,
      "servingUnit": "杯",
      "caloriesPerServing": 802,
      "proteinG": 32.1,
      "fatG": 26.7,
      "carbG": 108.3,
      "source": "ai_estimate",
      "sourceUrl": "https://storage.googleapis.com/studio-design-asset-files/projects/JpOL0L4xOQ/s-1x1_da3e772d-ae83-43cb-84d8-c867ddfe2fc7.pdf",
      "sourceCapturedAt": "2026-05-18"
    },
    {
      "name": "チャーシューごはん",
      "servingSizeG": 100,
      "servingUnit": "杯",
      "caloriesPerServing": 532,
      "proteinG": 21.3,
      "fatG": 17.7,
      "carbG": 71.8,
      "source": "ai_estimate",
      "sourceUrl": "https://storage.googleapis.com/studio-design-asset-files/projects/JpOL0L4xOQ/s-1x1_da3e772d-ae83-43cb-84d8-c867ddfe2fc7.pdf",
      "sourceCapturedAt": "2026-05-18"
    },
    {
      "name": "餃子（10個）",
      "servingSizeG": 100,
      "servingUnit": "杯",
      "caloriesPerServing": 337,
      "proteinG": 13.5,
      "fatG": 11.2,
      "carbG": 45.5,
      "source": "ai_estimate",
      "sourceUrl": "https://storage.googleapis.com/studio-design-asset-files/projects/JpOL0L4xOQ/s-1x1_da3e772d-ae83-43cb-84d8-c867ddfe2fc7.pdf",
      "sourceCapturedAt": "2026-05-18"
    },
    {
      "name": "ベジ麺 替玉（ラーメンのたれを含む）",
      "servingSizeG": 100,
      "servingUnit": "杯",
      "caloriesPerServing": 252,
      "proteinG": 10.1,
      "fatG": 8.4,
      "carbG": 34,
      "source": "ai_estimate",
      "sourceUrl": "https://storage.googleapis.com/studio-design-asset-files/projects/JpOL0L4xOQ/s-1x1_da3e772d-ae83-43cb-84d8-c867ddfe2fc7.pdf",
      "sourceCapturedAt": "2026-05-18"
    },
    {
      "name": "細麺 替玉（ラーメンのたれを含む）",
      "servingSizeG": 100,
      "servingUnit": "杯",
      "caloriesPerServing": 293,
      "proteinG": 11.7,
      "fatG": 9.8,
      "carbG": 39.6,
      "source": "ai_estimate",
      "sourceUrl": "https://storage.googleapis.com/studio-design-asset-files/projects/JpOL0L4xOQ/s-1x1_da3e772d-ae83-43cb-84d8-c867ddfe2fc7.pdf",
      "sourceCapturedAt": "2026-05-18"
    },
    {
      "name": "ガスパチョ冷麺(期間限定)",
      "servingSizeG": 100,
      "servingUnit": "杯",
      "caloriesPerServing": 852,
      "proteinG": 34.1,
      "fatG": 28.4,
      "carbG": 115,
      "source": "ai_estimate",
      "sourceUrl": "https://storage.googleapis.com/studio-design-asset-files/projects/JpOL0L4xOQ/s-1x1_da3e772d-ae83-43cb-84d8-c867ddfe2fc7.pdf",
      "sourceCapturedAt": "2026-05-18"
    },
    {
      "name": "原点",
      "servingSizeG": 100,
      "servingUnit": "杯",
      "caloriesPerServing": 680,
      "proteinG": 27.2,
      "fatG": 22.7,
      "carbG": 91.8,
      "source": "ai_estimate",
      "sourceUrl": "https://storage.googleapis.com/studio-design-asset-files/projects/JpOL0L4xOQ/s-1x1_da3e772d-ae83-43cb-84d8-c867ddfe2fc7.pdf",
      "sourceCapturedAt": "2026-05-18"
    },
    {
      "name": "赤丸新味",
      "servingSizeG": 100,
      "servingUnit": "杯",
      "caloriesPerServing": 830,
      "proteinG": 33.2,
      "fatG": 27.7,
      "carbG": 112.1,
      "source": "ai_estimate",
      "sourceUrl": "https://storage.googleapis.com/studio-design-asset-files/projects/JpOL0L4xOQ/s-1x1_da3e772d-ae83-43cb-84d8-c867ddfe2fc7.pdf",
      "sourceCapturedAt": "2026-05-18"
    },
    {
      "name": "本舗特製チャーハン",
      "servingSizeG": 100,
      "servingUnit": "杯",
      "caloriesPerServing": 831,
      "proteinG": 33.2,
      "fatG": 27.7,
      "carbG": 112.2,
      "source": "ai_estimate",
      "sourceUrl": "https://storage.googleapis.com/studio-design-asset-files/projects/JpOL0L4xOQ/s-1x1_da3e772d-ae83-43cb-84d8-c867ddfe2fc7.pdf",
      "sourceCapturedAt": "2026-05-18"
    },
    {
      "name": "店舗仕込み塩玉子",
      "servingSizeG": 100,
      "servingUnit": "杯",
      "caloriesPerServing": 66,
      "proteinG": 2.6,
      "fatG": 2.2,
      "carbG": 8.9,
      "source": "ai_estimate",
      "sourceUrl": "https://storage.googleapis.com/studio-design-asset-files/projects/JpOL0L4xOQ/s-1x1_da3e772d-ae83-43cb-84d8-c867ddfe2fc7.pdf",
      "sourceCapturedAt": "2026-05-18"
    },
    {
      "name": "肩ロースチャーシュー(2枚)",
      "servingSizeG": 100,
      "servingUnit": "杯",
      "caloriesPerServing": 39,
      "proteinG": 1.6,
      "fatG": 1.3,
      "carbG": 5.3,
      "source": "ai_estimate",
      "sourceUrl": "https://storage.googleapis.com/studio-design-asset-files/projects/JpOL0L4xOQ/s-1x1_da3e772d-ae83-43cb-84d8-c867ddfe2fc7.pdf",
      "sourceCapturedAt": "2026-05-18"
    },
    {
      "name": "柵バラチャーシュー(1枚)",
      "servingSizeG": 100,
      "servingUnit": "杯",
      "caloriesPerServing": 117,
      "proteinG": 4.7,
      "fatG": 3.9,
      "carbG": 15.8,
      "source": "ai_estimate",
      "sourceUrl": "https://storage.googleapis.com/studio-design-asset-files/projects/JpOL0L4xOQ/s-1x1_da3e772d-ae83-43cb-84d8-c867ddfe2fc7.pdf",
      "sourceCapturedAt": "2026-05-18"
    },
    {
      "name": "タンメン野菜",
      "servingSizeG": 100,
      "servingUnit": "杯",
      "caloriesPerServing": 120,
      "proteinG": 4.8,
      "fatG": 4,
      "carbG": 16.2,
      "source": "ai_estimate",
      "sourceUrl": "https://storage.googleapis.com/studio-design-asset-files/projects/JpOL0L4xOQ/s-1x1_da3e772d-ae83-43cb-84d8-c867ddfe2fc7.pdf",
      "sourceCapturedAt": "2026-05-18"
    },
    {
      "name": "白丸とんこつ",
      "servingSizeG": 100,
      "servingUnit": "杯",
      "caloriesPerServing": 663,
      "proteinG": 26.5,
      "fatG": 22.1,
      "carbG": 89.5,
      "source": "ai_estimate",
      "sourceUrl": "https://storage.googleapis.com/studio-design-asset-files/projects/JpOL0L4xOQ/s-1x1_da3e772d-ae83-43cb-84d8-c867ddfe2fc7.pdf",
      "sourceCapturedAt": "2026-05-18"
    },
    {
      "name": "赤丸とんこつ",
      "servingSizeG": 100,
      "servingUnit": "杯",
      "caloriesPerServing": 911,
      "proteinG": 36.4,
      "fatG": 30.4,
      "carbG": 123,
      "source": "ai_estimate",
      "sourceUrl": "https://storage.googleapis.com/studio-design-asset-files/projects/JpOL0L4xOQ/s-1x1_da3e772d-ae83-43cb-84d8-c867ddfe2fc7.pdf",
      "sourceCapturedAt": "2026-05-18"
    },
    {
      "name": "からか麺",
      "servingSizeG": 100,
      "servingUnit": "杯",
      "caloriesPerServing": 749,
      "proteinG": 30,
      "fatG": 25,
      "carbG": 101.1,
      "source": "ai_estimate",
      "sourceUrl": "https://storage.googleapis.com/studio-design-asset-files/projects/JpOL0L4xOQ/s-1x1_da3e772d-ae83-43cb-84d8-c867ddfe2fc7.pdf",
      "sourceCapturedAt": "2026-05-18"
    },
    {
      "name": "お子様ラーメン",
      "servingSizeG": 100,
      "servingUnit": "杯",
      "caloriesPerServing": 452,
      "proteinG": 18.1,
      "fatG": 15.1,
      "carbG": 61,
      "source": "ai_estimate",
      "sourceUrl": "https://storage.googleapis.com/studio-design-asset-files/projects/JpOL0L4xOQ/s-1x1_da3e772d-ae83-43cb-84d8-c867ddfe2fc7.pdf",
      "sourceCapturedAt": "2026-05-18"
    },
    {
      "name": "替玉(ラーメンのたれ含む)",
      "servingSizeG": 100,
      "servingUnit": "杯",
      "caloriesPerServing": 281,
      "proteinG": 11.2,
      "fatG": 9.4,
      "carbG": 37.9,
      "source": "ai_estimate",
      "sourceUrl": "https://storage.googleapis.com/studio-design-asset-files/projects/JpOL0L4xOQ/s-1x1_da3e772d-ae83-43cb-84d8-c867ddfe2fc7.pdf",
      "sourceCapturedAt": "2026-05-18"
    },
    {
      "name": "博多チャーハン(静岡SA店を除く)",
      "servingSizeG": 100,
      "servingUnit": "杯",
      "caloriesPerServing": 703,
      "proteinG": 28.1,
      "fatG": 23.4,
      "carbG": 94.9,
      "source": "ai_estimate",
      "sourceUrl": "https://storage.googleapis.com/studio-design-asset-files/projects/JpOL0L4xOQ/s-1x1_da3e772d-ae83-43cb-84d8-c867ddfe2fc7.pdf",
      "sourceCapturedAt": "2026-05-18"
    },
    {
      "name": "博多チャーハン(静岡SA店)",
      "servingSizeG": 100,
      "servingUnit": "杯",
      "caloriesPerServing": 850,
      "proteinG": 34,
      "fatG": 28.3,
      "carbG": 114.8,
      "source": "ai_estimate",
      "sourceUrl": "https://storage.googleapis.com/studio-design-asset-files/projects/JpOL0L4xOQ/s-1x1_da3e772d-ae83-43cb-84d8-c867ddfe2fc7.pdf",
      "sourceCapturedAt": "2026-05-18"
    },
    {
      "name": "博多ひとくち餃子(餃子のたれを含む)",
      "servingSizeG": 100,
      "servingUnit": "杯",
      "caloriesPerServing": 325,
      "proteinG": 13,
      "fatG": 10.8,
      "carbG": 43.9,
      "source": "ai_estimate",
      "sourceUrl": "https://storage.googleapis.com/studio-design-asset-files/projects/JpOL0L4xOQ/s-1x1_da3e772d-ae83-43cb-84d8-c867ddfe2fc7.pdf",
      "sourceCapturedAt": "2026-05-18"
    },
    {
      "name": "唐揚げ(4個)",
      "servingSizeG": 100,
      "servingUnit": "杯",
      "caloriesPerServing": 346,
      "proteinG": 13.8,
      "fatG": 11.5,
      "carbG": 46.7,
      "source": "ai_estimate",
      "sourceUrl": "https://storage.googleapis.com/studio-design-asset-files/projects/JpOL0L4xOQ/s-1x1_da3e772d-ae83-43cb-84d8-c867ddfe2fc7.pdf",
      "sourceCapturedAt": "2026-05-18"
    },
    {
      "name": "キャベツサラダ（唐揚げセット添え用）",
      "servingSizeG": 100,
      "servingUnit": "杯",
      "caloriesPerServing": 18,
      "proteinG": 0.7,
      "fatG": 0.6,
      "carbG": 2.4,
      "source": "ai_estimate",
      "sourceUrl": "https://storage.googleapis.com/studio-design-asset-files/projects/JpOL0L4xOQ/s-1x1_da3e772d-ae83-43cb-84d8-c867ddfe2fc7.pdf",
      "sourceCapturedAt": "2026-05-18"
    },
    {
      "name": "ポテトフライ",
      "servingSizeG": 100,
      "servingUnit": "杯",
      "caloriesPerServing": 575,
      "proteinG": 23,
      "fatG": 19.2,
      "carbG": 77.6,
      "source": "ai_estimate",
      "sourceUrl": "https://storage.googleapis.com/studio-design-asset-files/projects/JpOL0L4xOQ/s-1x1_da3e772d-ae83-43cb-84d8-c867ddfe2fc7.pdf",
      "sourceCapturedAt": "2026-05-18"
    },
    {
      "name": "チャーシューまぶしごはん",
      "servingSizeG": 100,
      "servingUnit": "杯",
      "caloriesPerServing": 446,
      "proteinG": 17.8,
      "fatG": 14.9,
      "carbG": 60.2,
      "source": "ai_estimate",
      "sourceUrl": "https://storage.googleapis.com/studio-design-asset-files/projects/JpOL0L4xOQ/s-1x1_da3e772d-ae83-43cb-84d8-c867ddfe2fc7.pdf",
      "sourceCapturedAt": "2026-05-18"
    },
    {
      "name": "明太子ごはん",
      "servingSizeG": 100,
      "servingUnit": "杯",
      "caloriesPerServing": 350,
      "proteinG": 14,
      "fatG": 11.7,
      "carbG": 47.3,
      "source": "ai_estimate",
      "sourceUrl": "https://storage.googleapis.com/studio-design-asset-files/projects/JpOL0L4xOQ/s-1x1_da3e772d-ae83-43cb-84d8-c867ddfe2fc7.pdf",
      "sourceCapturedAt": "2026-05-18"
    },
    {
      "name": "トッピング低温調理ロースチャーシュー（2枚）",
      "servingSizeG": 100,
      "servingUnit": "杯",
      "caloriesPerServing": 59,
      "proteinG": 2.4,
      "fatG": 2,
      "carbG": 8,
      "source": "ai_estimate",
      "sourceUrl": "https://storage.googleapis.com/studio-design-asset-files/projects/JpOL0L4xOQ/s-1x1_da3e772d-ae83-43cb-84d8-c867ddfe2fc7.pdf",
      "sourceCapturedAt": "2026-05-18"
    },
    {
      "name": "トッピング厚切りバラチャーシュー（１枚）",
      "servingSizeG": 100,
      "servingUnit": "杯",
      "caloriesPerServing": 124,
      "proteinG": 5,
      "fatG": 4.1,
      "carbG": 16.7,
      "source": "ai_estimate",
      "sourceUrl": "https://storage.googleapis.com/studio-design-asset-files/projects/JpOL0L4xOQ/s-1x1_da3e772d-ae83-43cb-84d8-c867ddfe2fc7.pdf",
      "sourceCapturedAt": "2026-05-18"
    },
    {
      "name": "トッピングきくらげ",
      "servingSizeG": 100,
      "servingUnit": "杯",
      "caloriesPerServing": 40,
      "proteinG": 1.6,
      "fatG": 1.3,
      "carbG": 5.4,
      "source": "ai_estimate",
      "sourceUrl": "https://storage.googleapis.com/studio-design-asset-files/projects/JpOL0L4xOQ/s-1x1_da3e772d-ae83-43cb-84d8-c867ddfe2fc7.pdf",
      "sourceCapturedAt": "2026-05-18"
    },
    {
      "name": "トッピングのり",
      "servingSizeG": 100,
      "servingUnit": "杯",
      "caloriesPerServing": 5,
      "proteinG": 0.2,
      "fatG": 0.2,
      "carbG": 0.7,
      "source": "ai_estimate",
      "sourceUrl": "https://storage.googleapis.com/studio-design-asset-files/projects/JpOL0L4xOQ/s-1x1_da3e772d-ae83-43cb-84d8-c867ddfe2fc7.pdf",
      "sourceCapturedAt": "2026-05-18"
    },
    {
      "name": "トッピングねぎ",
      "servingSizeG": 100,
      "servingUnit": "杯",
      "caloriesPerServing": 10,
      "proteinG": 0.4,
      "fatG": 0.3,
      "carbG": 1.4,
      "source": "ai_estimate",
      "sourceUrl": "https://storage.googleapis.com/studio-design-asset-files/projects/JpOL0L4xOQ/s-1x1_da3e772d-ae83-43cb-84d8-c867ddfe2fc7.pdf",
      "sourceCapturedAt": "2026-05-18"
    },
    {
      "name": "トッピングタンメン野菜",
      "servingSizeG": 100,
      "servingUnit": "杯",
      "caloriesPerServing": 120,
      "proteinG": 4.8,
      "fatG": 4,
      "carbG": 16.2,
      "source": "ai_estimate",
      "sourceUrl": "https://storage.googleapis.com/studio-design-asset-files/projects/JpOL0L4xOQ/s-1x1_da3e772d-ae83-43cb-84d8-c867ddfe2fc7.pdf",
      "sourceCapturedAt": "2026-05-18"
    },
    {
      "name": "トッピングメンマ",
      "servingSizeG": 100,
      "servingUnit": "杯",
      "caloriesPerServing": 12,
      "proteinG": 0.5,
      "fatG": 0.4,
      "carbG": 1.6,
      "source": "ai_estimate",
      "sourceUrl": "https://storage.googleapis.com/studio-design-asset-files/projects/JpOL0L4xOQ/s-1x1_da3e772d-ae83-43cb-84d8-c867ddfe2fc7.pdf",
      "sourceCapturedAt": "2026-05-18"
    },
    {
      "name": "トッピング辛味噌",
      "servingSizeG": 100,
      "servingUnit": "杯",
      "caloriesPerServing": 28,
      "proteinG": 1.1,
      "fatG": 0.9,
      "carbG": 3.8,
      "source": "ai_estimate",
      "sourceUrl": "https://storage.googleapis.com/studio-design-asset-files/projects/JpOL0L4xOQ/s-1x1_da3e772d-ae83-43cb-84d8-c867ddfe2fc7.pdf",
      "sourceCapturedAt": "2026-05-18"
    },
    {
      "name": "とんこつ醤油(みなとアクルス店限定)",
      "servingSizeG": 100,
      "servingUnit": "杯",
      "caloriesPerServing": 819,
      "proteinG": 32.8,
      "fatG": 27.3,
      "carbG": 110.6,
      "source": "ai_estimate",
      "sourceUrl": "https://storage.googleapis.com/studio-design-asset-files/projects/JpOL0L4xOQ/s-1x1_da3e772d-ae83-43cb-84d8-c867ddfe2fc7.pdf",
      "sourceCapturedAt": "2026-05-18"
    },
    {
      "name": "とんこつ濃厚味噌ラーメン(仙台港店限定)",
      "servingSizeG": 100,
      "servingUnit": "杯",
      "caloriesPerServing": 960,
      "proteinG": 38.4,
      "fatG": 32,
      "carbG": 129.6,
      "source": "ai_estimate",
      "sourceUrl": "https://storage.googleapis.com/studio-design-asset-files/projects/JpOL0L4xOQ/s-1x1_da3e772d-ae83-43cb-84d8-c867ddfe2fc7.pdf",
      "sourceCapturedAt": "2026-05-18"
    },
    {
      "name": "博多中華そば(柏の葉店、静岡SA店、ソラマチ店)",
      "servingSizeG": 100,
      "servingUnit": "杯",
      "caloriesPerServing": 630,
      "proteinG": 25.2,
      "fatG": 21,
      "carbG": 85.1,
      "source": "ai_estimate",
      "sourceUrl": "https://storage.googleapis.com/studio-design-asset-files/projects/JpOL0L4xOQ/s-1x1_da3e772d-ae83-43cb-84d8-c867ddfe2fc7.pdf",
      "sourceCapturedAt": "2026-05-18"
    },
    {
      "name": "朝ラーメン(静岡SA店限定、白ごはん、高菜付き)",
      "servingSizeG": 100,
      "servingUnit": "杯",
      "caloriesPerServing": 812,
      "proteinG": 32.5,
      "fatG": 27.1,
      "carbG": 109.6,
      "source": "ai_estimate",
      "sourceUrl": "https://storage.googleapis.com/studio-design-asset-files/projects/JpOL0L4xOQ/s-1x1_da3e772d-ae83-43cb-84d8-c867ddfe2fc7.pdf",
      "sourceCapturedAt": "2026-05-18"
    }
  ]
}
